CHANGELOG.rst
MANIFEST.in
README.rst
sc14n.py
setup.cfg
setup.py
sc14npy.egg-info/PKG-INFO
sc14npy.egg-info/SOURCES.txt
sc14npy.egg-info/dependency_links.txt
sc14npy.egg-info/top_level.txt
tests/AlicePrivRSASign.pem
tests/AliceRSASignByCarl.crt
tests/cdata-signed.xml
tests/context.py
tests/daiwei-base.xml
tests/daiwei-ents.xml
tests/daiwei.xml
tests/diawei-new.xml
tests/example1-excl-out.xml
tests/example1-incl-out.xml
tests/example1.xml
tests/example2-excl-out.xml
tests/example2-incl-out.xml
tests/example2.xml
tests/ignorable_ws.xml
tests/input.xml
tests/olamundo-base.xml
tests/olamundo-ds-xpath.xml
tests/olamundo-ds.xml
tests/olamundo-final-sha256.xml
tests/olamundo-final.xml
tests/olamundo-new.xml
tests/olamundo-new1.xml
tests/olamundo-signedinfo.xml
tests/olamundo-utf8.xml
tests/olamundo-utf8bom.xml
tests/olamundo.xml
tests/soap-ts3-signed-by-alice.xml
tests/test_sc14n.py
tests/test_sc14n_pki.py
tests/tests-xml.zip