Metadata-Version: 1.0
Name: sc14npy
Version: 2.1.1
Summary: A Python interface to SC14N
Home-page: https://www.cryptosys.net/sc14n/
Author: David Ireland
Author-email: UNKNOWN
License: UNKNOWN
Platform: Windows
